geneweaver/testing/__init__.py
geneweaver/testing/fixtures/__init__.py
geneweaver/testing/fixtures/package.py
geneweaver/testing/package/__init__.py
geneweaver/testing/package/can_import.py
geneweaver/testing/package/generic/__init__.py
geneweaver/testing/package/generic/pyproject.py
geneweaver/testing/package/generic/structure.py
geneweaver/testing/package/pyproject.py
geneweaver/testing/package/structure.py
geneweaver/testing/style/__init__.py
geneweaver/testing/style/black.py
geneweaver/testing/style/ruff.py
geneweaver_testing-0.1.2.dist-info/LICENSE
geneweaver_testing-0.1.2.dist-info/METADATA
geneweaver_testing-0.1.2.dist-info/WHEEL
geneweaver_testing-0.1.2.dist-info/RECORD
