Metadata-Version: 2.1
Name: geneweaver-testing
Version: 0.1.2
Summary: A library to standardize testing of GeneWeaver pacakges.
Home-page: https://thejacksonlaboratory.github.io/geneweaver-docs/
License: Apache-2.0
Author: Alexander Berger
Author-email: alexander.berger@jax.org
Requires-Python: >=3.8,<4.0
Classifier: License :: OSI Approved :: Apache Software License
Classifier: Programming Language :: Python :: 3
Classifier: Programming Language :: Python :: 3.8
Classifier: Programming Language :: Python :: 3.9
Classifier: Programming Language :: Python :: 3.10
Classifier: Programming Language :: Python :: 3.11
Classifier: Programming Language :: Python :: 3.12
Requires-Dist: black (>=24.2.0,<25.0.0)
Requires-Dist: isort (>=5.12.0,<6.0.0)
Requires-Dist: mypy (>=1.4.1,<2.0.0)
Requires-Dist: pytest (>=7.4.0,<9.0.0)
Requires-Dist: pytest-cov (>=4.1.0,<5.0.0)
Requires-Dist: radon (>=6.0.1,<7.0.0)
Requires-Dist: ruff (>=0.2.2,<0.3.0)
Requires-Dist: tomli (>=2.0.1,<3.0.0)
Project-URL: Repository, https://github.com/TheJacksonLaboratory/geneweaver-testing
